wowsql/__init__.py
wowsql/auth.py
wowsql/client.py
wowsql/schema.py
wowsql/storage.py
wowsql/table.py
wowsql/types.py
wowsql-1.3.0.dist-info/licenses/LICENSE
wowsql-1.3.0.dist-info/METADATA
wowsql-1.3.0.dist-info/WHEEL
wowsql-1.3.0.dist-info/top_level.txt
wowsql-1.3.0.dist-info/RECORD
