Metadata-Version: 2.4
Name: wowsql
Version: 1.3.0
Summary: Official Python SDK for WowSQL with project auth, S3 storage, SSL, and subdomain routing
Home-page: https://github.com/wowsql/wowsql
Author: WowSQL Team
Author-email: WowSQL Team <support@wowsql.com>
Project-URL: Homepage, https://wowsql.com
Project-URL: Documentation, https://docs.wowsql.com
Project-URL: Repository, https://github.com/wowsql/wowsql
Project-URL: Bug Tracker, https://github.com/wowsql/wowsql/issues
Keywords: wowsql,mysql,database,backend-as-a-service,baas,api,rest
Classifier: Development Status :: 5 - Production/Stable
Classifier: Intended Audience :: Developers
Classifier: Topic :: Software Development :: Libraries :: Python Modules
Classifier: License :: OSI Approved :: MIT License
Classifier: Programming Language :: Python :: 3
Classifier: Programming Language :: Python :: 3.8
Classifier: Programming Language :: Python :: 3.9
Classifier: Programming Language :: Python :: 3.10
Classifier: Programming Language :: Python :: 3.11
Classifier: Programming Language :: Python :: 3.12
Requires-Python: >=3.8
License-File: LICENSE
Requires-Dist: requests>=2.31.0
Requires-Dist: typing-extensions>=4.0.0
Provides-Extra: dev
Requires-Dist: pytest>=7.0.0; extra == "dev"
Requires-Dist: pytest-cov>=4.0.0; extra == "dev"
Requires-Dist: black>=23.0.0; extra == "dev"
Requires-Dist: mypy>=1.0.0; extra == "dev"
Dynamic: author
Dynamic: home-page
Dynamic: license-file
Dynamic: requires-python
